<?xml version="1.0" encoding="UTF-8"?>
<window id="139">
    <defaultcontrol always="true">5</defaultcontrol>
    <controls>
        <include>Background_Overlay</include>
        <control type="group">
            <include content="Def_Dialog_InfoPanel"><param name="height" value="764" /><param name="width" value="900" /><param name="colordiffuse" value="Panel" /></include>

            <control type="label">
                <include>Def_Dialog_Header_Title</include>
                <label>13406</label>
            </control>

            <include>Def_Dialog_Header_Logo</include>
            <include>Def_Dialog_Header_Line</include>

            <control type="list" id="5">
                <left>30</left>
                <top>112</top>
                <width>838</width>
                <height>552</height>
                <onleft>Close</onleft>
                <onright>Close</onright>
                <onup>5</onup>
                <ondown>5</ondown>
                <itemlayout height="69" width="838">
                    <control type="image">
                        <width>838</width>
                        <height>66</height>
                        <texture colordiffuse="Black12">common/white.png</texture>
                    </control>
                    <control type="label">
                        <left>30</left>
                        <width>405</width>
                        <label>$INFO[ListItem.Label]</label>
                    </control>
                    <control type="label">
                        <right>30</right>
                        <width>405</width>
                        <align>right</align>
                        <font>Tiny</font>
                        <label>$INFO[ListItem.Label2]</label>
                    </control>
                </itemlayout>
                <focusedlayout height="69" width="838">
                    <control type="image">
                        <width>838</width>
                        <height>66</height>
                        <texture>special://profile/addon_data/script.texturemaker/ArcticZephirRounded/main_h.png</texture>
                    </control>
                    <control type="label">
                        <left>30</left>
                        <width>405</width>
                        <textcolor>Selected</textcolor>
                        <label>$INFO[ListItem.Label]</label>
                    </control>
                    <control type="label">
                        <right>30</right>
                        <width>405</width>
                        <align>right</align>
                        <font>Tiny</font>
                        <textcolor>Selected</textcolor>
                        <label>$INFO[ListItem.Label2]</label>
                    </control>
                </focusedlayout>
            </control>
            <include>Def_Dialog_Select_label_Num_Item</include>
        </control>
    </controls>
</window>
